coapmids/__init__.py
coapmids/blockwise.py
coapmids/credentials.py
coapmids/defaults.py
coapmids/error.py
coapmids/interfaces.py
coapmids/message.py
coapmids/messagemanager.py
coapmids/meta.py
coapmids/options.py
coapmids/optiontypes.py
coapmids/oscore.py
coapmids/oscore_sitewrapper.py
coapmids/pipe.py
coapmids/protocol.py
coapmids/resource.py
coapmids/tokenmanager.py
coapmids/cli/__init__.py
coapmids/cli/client.py
coapmids/cli/common.py
coapmids/cli/defaults.py
coapmids/cli/fileserver.py
coapmids/cli/proxy.py
coapmids/cli/rd.py
coapmids/numbers/__init__.py
coapmids/numbers/codes.py
coapmids/numbers/constants.py
coapmids/numbers/contentformat.py
coapmids/numbers/optionnumbers.py
coapmids/numbers/types.py
coapmids/proxy/__init__.py
coapmids/proxy/client.py
coapmids/proxy/server.py
coapmids/resourcedirectory/__init__.py
coapmids/resourcedirectory/client/__init__.py
coapmids/resourcedirectory/client/register.py
coapmids/transports/__init__.py
coapmids/transports/generic_udp.py
coapmids/transports/oscore.py
coapmids/transports/rfc8323common.py
coapmids/transports/simple6.py
coapmids/transports/simplesocketserver.py
coapmids/transports/tcp.py
coapmids/transports/tinydtls.py
coapmids/transports/tinydtls_server.py
coapmids/transports/tls.py
coapmids/transports/udp6.py
coapmids/transports/ws.py
coapmids/util/__init__.py
coapmids/util/cli.py
coapmids/util/contenttype.py
coapmids/util/cryptography_additions.py
coapmids/util/linkformat.py
coapmids/util/linkformat_pygments.py
coapmids/util/prettyprint.py
coapmids/util/pyodide_websockets.py
coapmids/util/socknumbers.py
coapmids/util/uri.py
coapmids/util/asyncio/__init__.py
coapmids/util/asyncio/getaddrinfo_addrconfig.py
coapmids/util/asyncio/recvmsg.py
coapmids/util/asyncio/timeoutdict.py
coapmids/util/vendored/link_header.py
coapmids-0.0.18.dist-info/LICENSE
coapmids-0.0.18.dist-info/METADATA
coapmids-0.0.18.dist-info/WHEEL
coapmids-0.0.18.dist-info/top_level.txt
coapmids-0.0.18.dist-info/RECORD
